Metadata-Version: 1.1
Name: sl-docformatter
Version: 1.4
Summary: Formats docstrings to follow PEP 257.
Home-page: https://github.com/myint/docformatter
Author: Steven Myint
Author-email: UNKNOWN
License: Expat License
Keywords: PEP 257,pep257,style,formatter,docstrings
Platform: UNKNOWN
Classifier: Intended Audience :: Developers
Classifier: Environment :: Console
Classifier: Programming Language :: Python :: 2.7
Classifier: Programming Language :: Python :: 3
Classifier: License :: OSI Approved :: MIT License
